yoncrawler/__init__.py
yoncrawler/constructor.py
yoncrawler/crawlers/__init__.py
yoncrawler/crawlers/as_crawler.py
yoncrawler/crawlers/base_cralwer.py
yoncrawler/crawlers/cs_crawler.py
yoncrawler/crawlers/ec_crawler.py
yoncrawler/crawlers/sb_crawler.py
yoncrawler/crawlers/yonsei_crawler.py
yoncrawler/db/__init__.py
yoncrawler/db/base_db.py
yoncrawler/db/mongo_db.py
yoncrawler/db/simple_db.py
yoncrawler/util/__init__.py
yoncrawler/util/logger.py
yoncrawler/util/parse_module.py
yoncrawler/util/request_module.py
yoncrawler-0.1.0.dist-info/LICENSE
yoncrawler-0.1.0.dist-info/METADATA
yoncrawler-0.1.0.dist-info/WHEEL
yoncrawler-0.1.0.dist-info/top_level.txt
yoncrawler-0.1.0.dist-info/RECORD
