Metadata-Version: 2.1
Name: yoncrawler
Version: 0.1.0
Summary: 연세대학교의 공지사항을 쉽게 크롤링할 수 있는 패키지입니다.
Home-page: https://github.com/xodhx4/YonseiNotice
Author: Taeoh Kim
Author-email: kimtaeoh95@gmail.com
License: MIT license
Keywords: yoncrawler,연세대,공지,크롤러
Platform: UNKNOWN
Classifier: Development Status :: 2 - Pre-Alpha
Classifier: Intended Audience :: Developers
Classifier: License :: OSI Approved :: MIT License
Classifier: Natural Language :: English
Classifier: Programming Language :: Python :: 3
Classifier: Programming Language :: Python :: 3.6
Classifier: Programming Language :: Python :: 3.7
Requires-Python: >=3, !=3.0.*, !=3.1.*, !=3.2.*, !=3.3.*, !=3.4.*, !=3.5.*
Requires-Dist: beautifulsoup4
Requires-Dist: pymongo
Requires-Dist: requests
Requires-Dist: tinydb
